{
    "ChatMessageDecoder": 0,
    "WebSocketChatServer": 0,
    "ChatMessageEncoder": 0,
    "ChatMessage": 0,
    "Advertisement": 1,
    "AdvertisementImpl": 1,
    "FileManager": 2,
    "CommentValidator": 3,
    "UserTab": 3,
    "Admin": 3,
    "Database": 4,
    "Search": 5,
    "CommentTab": 5,
    "OtherInfo": 6,
    "DebugInfo": 6,
    "RuntimeNamedQueryInitializer": 7,
    "AppContextLister": 7,
    "Login": 8,
    "ReadImage": 9,
    "WebConfig": 9,
    "WeatherREST": 10,
    "WeatherForecast": 10,
    "SessionListener": 10,
    "Ticker": 10,
    "TestInterceptor": 10,
    "GetWeatherJPA": 11,
    "AdvertisementImplService": 11,
    "WeatherForecastFactory": 11,
    "AdvertisementFactory": 11,
    "GetWeatherJPAResponse": 11,
    "GetAdsByIDJPA": 11,
    "ObjectFactory [Duplicate_#001]": 11,
    "GetAdsByIDJPAResponse": 11,
    "ObjectFactory": 11,
    "WeatherForecastService": 11,
    "Weather": 12,
    "DBConn": 13,
    "Talk": 13,
    "LoginFilter": 13,
    "ContextConfig": 13,
    "CQuery": 14,
    "SettingsHandler": 15,
    "SettingValues": 15,
    "Advertise": 16,
    "Color": 16,
    "Zodiac": 16,
    "Extension": 16,
    "WebSummary": 16
}