{
    "ChatMessageDecoder": 0,
    "WebSocketChatServer": 0,
    "ChatMessageEncoder": 0,
    "ChatMessage": 0,
    "AppContextLister": 1,
    "GetWeatherJPA": 1,
    "AdvertisementImplService": 1,
    "WeatherForecastFactory": 1,
    "AdvertisementFactory": 1,
    "GetWeatherJPAResponse": 1,
    "GetAdsByIDJPA": 1,
    "ObjectFactory [Duplicate_#001]": 1,
    "GetAdsByIDJPAResponse": 1,
    "ObjectFactory": 1,
    "WeatherForecastService": 1,
    "WeatherForecast": 2,
    "Database": 2,
    "FileManager": 2,
    "Search": 2,
    "OtherInfo": 2,
    "DebugInfo": 2,
    "Ticker": 3,
    "TestInterceptor": 3,
    "Login": 3,
    "CommentValidator": 4,
    "CommentTab": 4,
    "Advertise": 5,
    "Color": 5,
    "Zodiac": 5,
    "Extension": 5,
    "Talk": 5,
    "LoginFilter": 5,
    "Advertisement": 5,
    "AdvertisementImpl": 5,
    "SettingsHandler": 5,
    "SettingValues": 5,
    "ReadImage": 5,
    "WebConfig": 5,
    "WeatherREST": 5,
    "SessionListener": 5,
    "WebSummary": 5,
    "ContextConfig": 5,
    "DBConn": 5,
    "CQuery": 6,
    "RuntimeNamedQueryInitializer": 6,
    "UserTab": 6,
    "Weather": 6,
    "Admin": 6
}